direnumerate/__init__.py
direnumerate/__main__.py
direnumerate/banner.py
direnumerate/cli.py
direnumerate/colors.py
direnumerate/createlist.py
direnumerate/exceptions.py
direnumerate/help.py
direnumerate/ipcalculator.py
direnumerate/port_scan.py
direnumerate/version.py
direnumerate/warning.py
direnumerate-4.1.0.dist-info/LICENSE
direnumerate-4.1.0.dist-info/METADATA
direnumerate-4.1.0.dist-info/WHEEL
direnumerate-4.1.0.dist-info/entry_points.txt
direnumerate-4.1.0.dist-info/top_level.txt
direnumerate-4.1.0.dist-info/RECORD
